torch_geometric_signed_directed/__init__.py
torch_geometric_signed_directed/data/__init__.py
torch_geometric_signed_directed/data/directed/DIGRAC_real_data.py
torch_geometric_signed_directed/data/directed/DSBM.py
torch_geometric_signed_directed/data/directed/DirectedData.py
torch_geometric_signed_directed/data/directed/Telegram.py
torch_geometric_signed_directed/data/directed/WikiCS.py
torch_geometric_signed_directed/data/directed/WikipediaNetwork.py
torch_geometric_signed_directed/data/directed/__init__.py
torch_geometric_signed_directed/data/directed/citation.py
torch_geometric_signed_directed/data/directed/load_directed_real_data.py
torch_geometric_signed_directed/data/general/SDSBM.py
torch_geometric_signed_directed/data/general/__init__.py
torch_geometric_signed_directed/data/signed/MSGNN_real_data.py
torch_geometric_signed_directed/data/signed/SDGNN_real_data.py
torch_geometric_signed_directed/data/signed/SSBM.py
torch_geometric_signed_directed/data/signed/SSSNET_real_data.py
torch_geometric_signed_directed/data/signed/SignedData.py
torch_geometric_signed_directed/data/signed/__init__.py
torch_geometric_signed_directed/data/signed/load_signed_real_data.py
torch_geometric_signed_directed/data/signed/polarized_SSBM.py
torch_geometric_signed_directed/nn/__init__.py
torch_geometric_signed_directed/nn/directed/DGCNConv.py
torch_geometric_signed_directed/nn/directed/DGCN_link_prediction.py
torch_geometric_signed_directed/nn/directed/DGCN_node_classification.py
torch_geometric_signed_directed/nn/directed/DIGRAC_node_clustering.py
torch_geometric_signed_directed/nn/directed/DIMPA.py
torch_geometric_signed_directed/nn/directed/DiGCL.py
torch_geometric_signed_directed/nn/directed/DiGCNConv.py
torch_geometric_signed_directed/nn/directed/DiGCN_Inception_Block.py
torch_geometric_signed_directed/nn/directed/DiGCN_Inception_Block_link_prediction.py
torch_geometric_signed_directed/nn/directed/DiGCN_Inception_Block_node_classification.py
torch_geometric_signed_directed-0.25.0.dist-info/LICENSE
torch_geometric_signed_directed-0.25.0.dist-info/METADATA
torch_geometric_signed_directed-0.25.0.dist-info/WHEEL
torch_geometric_signed_directed-0.25.0.dist-info/top_level.txt
torch_geometric_signed_directed-0.25.0.dist-info/RECORD
