Metadata-Version: 2.1
Name: torch-geometric-signed-directed
Version: 0.25.0
Summary: An Extension Library for PyTorch Geometric on signed and directed networks.
Home-page: https://github.com/SherylHYX/pytorch_geometric_signed_directed
Download-URL: https://github.com/SherylHYX/pytorch_geometric_signed_directed/archive/0.25.0.tar.gz
Author: Yixuan He
Author-email: yixuan.he@balliol.ox.ac.uk
License: MIT
Keywords: machine-learning,deep-learning,deeplearning,deep learning,machine learning,signal processing,signed graph,graph,directed graph,embedding,clustering,graph convolution,graph neural network,representation learning,learning
Classifier: Intended Audience :: Developers
Classifier: Topic :: Software Development :: Build Tools
Classifier: License :: OSI Approved :: MIT License
Classifier: Programming Language :: Python :: 3.7
Requires-Python: >=3.7
License-File: LICENSE
Requires-Dist: torch
Requires-Dist: torch-sparse
Requires-Dist: scikit-learn
Requires-Dist: torch-geometric
Requires-Dist: numpy
Requires-Dist: networkx <2.7
Requires-Dist: scipy
